{
  "$schema": "http://json-schema.org/draft-07/schema#",
  "type": "object",
  "properties": {
    "albums": {
      "type": "array",
      "items": {
        "type": "object",
        "properties": {
          "album_type": {
            "type": "string",
            "enum": ["album", "single", "compilation"]
          },
          "total_tracks": {
            "type": "integer"
          },
          "available_markets": {
            "type": "array",
            "items": {
              "type": "string"
            }
          },
          "external_urls": {
            "type": "object",
            "properties": {
              "spotify": {
                "type": "string"
              }
            },
            "required": ["spotify"]
          },
          "href": {
            "type": "string"
          },
          "id": {
            "type": "string"
          },
          "images": {
            "type": "array",
            "items": {
              "type": "object",
              "properties": {
                "url": {
                  "type": "string"
                },
                "height": {
                  "type": "integer"
                },
                "width": {
                  "type": "integer"
                }
              },
              "required": ["url", "height", "width"]
            }
          },
          "name": {
            "type": "string"
          },
          "release_date": {
            "type": "string"
          },
          "release_date_precision": {
            "type": "string",
            "enum": ["year", "month", "day"]
          },
          "restrictions": {
            "type": "object",
            "properties": {
              "reason": {
                "type": "string"
              }
            }
          },
          "type": {
            "type": "string",
            "enum": ["album"]
          },
          "uri": {
            "type": "string"
          },
          "artists": {
            "type": "array",
            "items": {
              "type": "object",
              "properties": {
                "external_urls": {
                  "type": "object",
                  "properties": {
                    "spotify": {
                      "type": "string"
                    }
                  },
                  "required": ["spotify"]
                },
                "href": {
                  "type": "string"
                },
                "id": {
                  "type": "string"
                },
                "name": {
                  "type": "string"
                },
                "type": {
                  "type": "string"
                },
                "uri": {
                  "type": "string"
                }
              },
              "required": ["external_urls", "href", "id", "name", "type", "uri"]
            }
          },
          "tracks": {
            "type": "object",
            "properties": {
              "href": {
                "type": "string"
              },
              "limit": {
                "type": "integer"
              },
              "next": {
                "type": ["string", "null"]
              },
              "offset": {
                "type": "integer"
              },
              "previous": {
                "type": ["string", "null"]
              },
              "total": {
                "type": "integer"
              },
              "items": {
                "type": "array",
                "items": {
                  "type": "object",
                  "properties": {
                    "artists": {
                      "type": "array",
                      "items": {
                        "type": "object",
                        "properties": {
                          "external_urls": {
                            "type": "object",
                            "properties": {
                              "spotify": {
                                "type": "string"
                              }
                            },
                            "required": ["spotify"]
                          },
                          "href": {
                            "type": "string"
                          },
                          "id": {
                            "type": "string"
                          },
                          "name": {
                            "type": "string"
                          },
                          "type": {
                            "type": "string"
                          },
                          "uri": {
                            "type": "string"
                          }
                        },
                        "required": ["external_urls", "href", "id", "name", "type", "uri"]
                      }
                    },
                    "available_markets": {
                      "type": "array",
                      "items": {
                        "type": "string"
                      }
                    },
                    "disc_number": {
                      "type": "integer"
                    },
                    "duration_ms": {
                      "type": "integer"
                    },
                    "explicit": {
                      "type": "boolean"
                    },
                    "external_urls": {
                      "type": "object",
                      "properties": {
                        "spotify": {
                          "type": "string"
                        }
                      },
                      "required": ["spotify"]
                    },
                    "href": {
                      "type": "string"
                    },
                    "id": {
                      "type": "string"
                    },
                    "is_playable": {
                      "type": "boolean"
                    },
                    "linked_from": {
                      "type": ["object", "null"],
                      "properties": {
                        "external_urls": {
                          "type": "object",
                          "properties": {
                            "spotify": {
                              "type": "string"
                            }
                          }
                        },
                        "href": {
                          "type": "string"
                        },
                        "id": {
                          "type": "string"
                        },
                        "type": {
                          "type": "string"
                        },
                        "uri": {
                          "type": "string"
                        }
                      }
                    },
                    "restrictions": {
                      "type": ["object", "null"]
                    },
                    "name": {
                      "type": "string"
                    },
                    "preview_url": {
                      "type": ["string", "null"]
                    },
                    "track_number": {
                      "type": "integer"
                    },
                    "type": {
                      "type": "string"
                    },
                    "uri": {
                      "type": "string"
                    },
                    "is_local": {
                      "type": "boolean"
                    }
                  },
                  "required": [
                    "artists",
                    "available_markets",
                    "disc_number",
                    "duration_ms",
                    "explicit",
                    "external_urls",
                    "href",
                    "id",
                    "is_playable",
                    "name",
                    "track_number",
                    "type",
                    "uri",
                    "is_local"
                  ]
                }
              }
            },
            "required": ["href", "limit", "offset", "total", "items"]
          },
          "copyrights": {
            "type": "array",
            "items": {
              "type": "object",
              "properties": {
                "text": {
                  "type": "string"
                },
                "type": {
                  "type": "string"
                }
              },
              "required": ["text", "type"]
            }
          },
          "external_ids": {
            "type": "object",
            "properties": {
              "isrc": {
                "type": "string"
              },
              "ean": {
                "type": "string"
              },
              "upc": {
                "type": "string"
              }
            }
          },
          "genres": {
            "type": "array",
            "items": {
              "type": "string"
            }
          },
          "label": {
            "type": "string"
          },
          "popularity": {
            "type": "integer"
          }
        },
        "required": [
          "album_type",
          "total_tracks",
          "available_markets",
          "external_urls",
          "href",
          "id",
          "images",
          "name",
          "release_date",
          "release_date_precision",
          "type",
          "uri",
          "artists",
          "tracks",
          "copyrights",
          "external_ids",
          "genres",
          "label",
          "popularity"
        ]
      }
    }
  },
  "required": ["albums"]
}